{
  "slug": "chicago-pd-season-13-finale-voights-fate-revealed",
  "title": "Chicago PD Season 13 Finale: Voight's Fate Revealed",
  "body": "The latest season finale of the hit television series Chicago P.D. has left fans reeling with a dramatic cliffhanger that raises questions about the future of two key characters. The intense episode culminated in a shocking confrontation between Imani, a complex and intriguing character, and an officer, which ultimately led to the officer being overpowered and restrained. As the situation spiralled out of control, Imani's sister was drawn into the chaos, and the character's actions sparked a chain of events that will have significant repercussions in the upcoming season. The finale's ending has sparked a heated debate among fans, with many wondering whether Voight, a central figure in the series, will choose to cover for Imani or take a different course of action.\n\nAt the heart of the controversy is the intricate relationship between Imani and Voight, which has been a focal point of the series throughout the season. Their complex dynamic has been expertly woven into the narrative, with each character influencing the other in profound ways. As the story unfolded, it became clear that Imani's actions were motivated by a desire to protect her sister, even if it meant putting herself and others at risk. This moral ambiguity has sparked a lively discussion among fans, with some arguing that Imani's actions were justified, while others believe that she crossed a line that cannot be ignored.\n\nThe show's creators have masterfully crafted a narrative that challenges viewers to question their assumptions about right and wrong. By presenting a scenario in which a character is forced to make a difficult choice, the series invites fans to consider the complexities of human nature and the motivations that drive people to act in certain ways. This nuanced approach to storytelling has been a hallmark of the series, and it is a key factor in its enduring popularity. As the debate over Imani's actions continues to rage, it is clear that the show's creators have once again succeeded in pushing the boundaries of what is expected from a television drama.\n\nIn the aftermath of the season finale, fans are eagerly awaiting the next installment to see how the story will unfold. One of the key questions on everyone's mind is whether Voight will choose to cover for Imani, potentially putting his own career at risk. This decision will have significant implications for the characters and the overall narrative, and it is likely to be a major plot point in the upcoming season. As the show's writers and actors work to craft a compelling and believable storyline, they will need to carefully consider the consequences of Voight's actions and how they will impact the characters and the audience.\n\nThe season finale's cliffhanger ending has also sparked a broader conversation about the themes and messages that underlie the series. Chicago P.D. has long been praised for its thoughtful exploration of complex social issues, and the latest season has been no exception. By tackling topics such as trauma, loyalty, and the moral gray areas that exist in law enforcement, the show's creators have demonstrated a commitment to creating a narrative that is both entertaining and thought-provoking. As the series continues to evolve and grow, it is likely that these themes will remain at the forefront, challenging fans to think critically about the world around them.\n\nAs fans eagerly await the next season of Chicago P.D., one thing is clear: the show's creators have set the stage for a dramatic and intense storyline that will keep viewers on the edge of their seats. With the fate of Imani and Voight hanging in the balance, the upcoming season is poised to be one of the most exciting and unpredictable yet. As the story continues to unfold, it is likely that fans will be treated to a rollercoaster ride of twists and turns, each one challenging their assumptions and keeping them guessing until the very end. With its masterful storytelling, complex characters, and thought-provoking themes, Chicago P.D. is sure to remain a fan favourite for years to come.",
  "category": "Entertainment",
  "image": "https://www.tvline.com/img/gallery/chicago-p-d-arienne-mandi-showrunner-unpack-imanis-finale-heartbreak-plus-will-voight-break-more-rules-in-season-14/l-intro-1778715603.jpg",
  "image_source": "",
  "date": "2026-05-15T14:12:37Z",
  "tags": [
    "Entertainment"
  ],
  "source_url": "https://www.tvline.com/2172542/chicago-pd-season-13-finale-ending-explained-voight-imani/",
  "discover": true
}