{
  "slug": "balogun-scores-2-in-us-world-cup-debut-snubs-england-and-nigeria",
  "title": "Balogun scores 2 in US World Cup debut, snubs England and Nigeria.",
  "body": "In a thrilling World Cup debut, young American striker Folarin Balogun made a stunning impact, scoring two crucial goals in the United States' 4-1 victory over Paraguay. The highly anticipated match, played in front of a packed crowd of 70,492 spectators in Inglewood, California, marked a triumphant beginning to the Americans' World Cup campaign. Balogun's impressive performance not only showcased his exceptional skills but also highlighted his wise decision to represent the United States, a country he could have easily overlooked in favor of England or Nigeria, two other nations he was eligible to play for.\n\nBalogun's journey to the World Cup stage is a fascinating one, with the 24-year-old striker having had the opportunity to don the jerseys of three different countries. Born with the option to play for England, Nigeria, or the United States, Balogun ultimately chose to pledge his allegiance to the Stars and Stripes. This decision has been widely hailed as a significant coup for American soccer, with many pundits believing that Balogun's arrival could be a game-changer for the national team. His World Cup debut has only served to reinforce this notion, with the young striker's pace, skill, and finishing ability leaving fans and commentators alike in awe.\n\nThe United States' victory over Paraguay was a comprehensive one, with the team's attacking lineup, led by Balogun, causing consistent problems for the opposition defense. The Americans' 4-1 win was a testament to their strength and depth, with Balogun's two goals providing the catalyst for the team's success. His first strike, a beautifully crafted effort that showcased his lightning-quick reflexes and precision finishing, set the tone for the match, while his second goal, a powerful header, effectively sealed the win for the United States. As the American team celebrated their hard-fought victory, Balogun's name was on everyone's lips, with many hailing him as a potential star of the tournament.\n\nAs the World Cup progresses, all eyes will be on Balogun to see if he can maintain his impressive form and lead the United States deep into the competition. With his debut performance having set such a high standard, expectations will be sky-high, but the young striker appears to have the talent, confidence, and dedication required to rise to the challenge. The United States' coaching staff will be delighted with the options at their disposal, with Balogun's arrival adding a new dimension to the team's attack. As the tournament unfolds, it will be fascinating to see how the Americans utilize their new star player and how Balogun responds to the intense scrutiny and pressure that comes with playing on the world stage.\n\nThe implications of Balogun's decision to play for the United States extend far beyond the current World Cup campaign. His arrival has the potential to inspire a new generation of American soccer players, while his success could help to attract other top talents to the national team. As the sport continues to grow in popularity across the United States, the presence of a charismatic and talented player like Balogun could be a major factor in its development. With the United States set to host the World Cup in the future, the country's soccer fans will be eager to see their team compete with the best nations in the world, and Balogun's emergence has provided a significant boost to their hopes of success.\n\nAs the World Cup continues to captivate audiences around the globe, Folarin Balogun's star is firmly on the rise. With his impressive debut performance having set the tone for the United States' campaign, the young striker will be eager to build on his success and lead his team to glory. As the tournament progresses, one thing is certain \u2013 Balogun will be a player to watch, and his journey will be followed with great interest by soccer fans everywhere. With the United States' next match just around the corner, the stage is set for Balogun to continue his impressive form and write his name into the history books as one of the stars of the World Cup.",
  "category": "Sports",
  "image": "https://dims.apnews.com/dims4/default/2ac8af5/2147483647/strip/true/crop/8640x5757+0+1/resize/980x653!/quality/90/?url=https%3A%2F%2Fassets.apnews.com%2Fdd%2F25%2F6607da67a1c40e0f2990a2ffecde%2F1310733bdb2a4efc8303467c00f8fdde",
  "image_source": "",
  "date": "2026-06-14T16:23:47Z",
  "tags": [
    "Sports"
  ],
  "source_url": "https://apnews.com/article/world-cup-folarin-balogun-usmnt-81fe1dd7b8b391aff8fe55a711fd7028",
  "discover": true
}