{
  "slug": "cavaliers-pistons-game-7-nba-playoffs-2026-live-updates",
  "title": "Cavaliers-Pistons Game 7: NBA Playoffs 2026 Live Updates",
  "body": "In a decisive Game 7 showdown, the Cleveland Cavaliers dominated the Detroit Pistons, securing a spot in the Eastern Conference finals with a resounding blowout victory on Sunday. The Cavaliers' impressive performance was fueled by a strong second and third quarter, which set the tone for the remainder of the game and ultimately led to their advancement in the playoffs. As the final buzzer sounded, the Cavaliers' triumphant celebration was a testament to their unwavering dedication and unrelenting passion for the sport. The convincing win marked a significant milestone in the team's postseason journey, and fans are eagerly anticipating their next challenge.\n\nThe Cavaliers' success can be attributed to their ability to adapt and evolve throughout the series. After facing intense competition from the Pistons, they regrouped and refocused, emerging with a renewed sense of purpose and determination. The team's cohesion and chemistry were on full display, as they worked together seamlessly to outmaneuver their opponents and capitalize on scoring opportunities. The Cavaliers' bench also played a crucial role, providing a much-needed spark and injecting energy into the game. As the series progressed, the team's resilience and perseverance became increasingly evident, and their Game 7 victory was a culmination of their hard work and perseverance.\n\nThe Detroit Pistons, on the other hand, struggled to maintain momentum and consistency throughout the series. Despite their valiant efforts, they were unable to overcome the Cavaliers' formidable offense and stifling defense. The Pistons' inability to contain the Cavaliers' scoring threats ultimately proved to be their downfall, as they were outscored and outplayed in the decisive Game 7. While the loss was undoubtedly disappointing, the Pistons can take pride in their impressive postseason run and the experience they gained along the way. As they look to the future, they will undoubtedly regroup and reassess their strategy, with a focus on building a stronger, more competitive team.\n\nThe Cavaliers' advancement to the Eastern Conference finals marks a significant turning point in the playoffs, as the competition is expected to intensify in the coming weeks. As they prepare to face their next opponent, the Cavaliers will need to remain focused and composed, drawing on the lessons they learned from their series against the Pistons. With their sights set on the championship title, the Cavaliers will be pushed to their limits, and their resolve and determination will be tested like never before. The question on everyone's mind is: can they maintain their current level of performance and make a deep run in the playoffs?\n\nAs the NBA playoffs continue to unfold, fans are eagerly anticipating the next installment of the high-stakes competition. The Cavaliers' journey to the Eastern Conference finals has been nothing short of remarkable, and their story is far from over. With the stakes higher than ever, the Cavaliers will need to summon every ounce of skill, strategy, and grit to overcome their upcoming challenges. As the basketball world watches with bated breath, one thing is certain: the Cleveland Cavaliers are a force to be reckoned with, and their quest for greatness is only just beginning.\n\nIn the days and weeks to come, the Cavaliers will face unprecedented pressure and scrutiny, as they vie for a spot in the NBA Finals. However, based on their impressive performance in Game 7, it is clear that they have the talent, the depth, and the determination to make a serious push for the championship title. As the city of Cleveland rallies behind their team, the Cavaliers will undoubtedly draw energy and inspiration from their loyal fan base. With their eyes fixed firmly on the prize, the Cavaliers are poised to make a lasting impact on the NBA playoffs, and their journey is one that will be closely watched and eagerly anticipated by fans around the world.",
  "category": "Sports",
  "image": "https://a3.espncdn.com/combiner/i?img=%2Fphoto%2F2026%2F0518%2Fr1659602_1296x729_16%2D9.jpg",
  "image_source": "",
  "date": "2026-05-19T03:46:35Z",
  "tags": [
    "Sports"
  ],
  "source_url": "https://www.espn.com/nba/story/_/id/48798707/detroit-pistons-cleveland-cavaliers-game-7-nba-playoffs-2026-live-updates-results-moments",
  "discover": true
}