{
  "slug": "celtics-vs-76ers-nba-playoffs-game-6-picks-and-odds",
  "title": "Celtics vs 76ers NBA Playoffs Game 6 Picks and Odds",
  "body": "The stage is set for a thrilling conclusion to the first-round NBA playoff series between the Boston Celtics and the Philadelphia 76ers, as the two teams prepare to face off in Game 6 this Thursday. With the Celtics currently holding a 3-2 lead, the 76ers will be looking to even the series and force a deciding Game 7. The energy is expected to be electric at the Xfinity Mobile Arena in South Philadelphia, where the 76ers will be counting on the support of their home crowd to propel them to victory. Tipoff is scheduled for 8:00 p.m., and fans can expect a fiercely competitive contest between two teams that have been evenly matched throughout the series.\n\nThe Celtics have been led by their strong team defense, which has been able to contain the 76ers' high-powered offense and limit their scoring opportunities. However, the 76ers have shown flashes of brilliance on offense, and their ability to score from both inside and outside the paint makes them a formidable opponent. The Celtics will need to be at the top of their game defensively if they hope to shut down the 76ers and advance to the next round. On the other hand, the 76ers will be looking to exploit any weaknesses in the Celtics' defense and get their offense rolling early in the game.\n\nOne of the key factors that could determine the outcome of Game 6 is the performance of the 76ers' star players. If they can get their top scorers going early and often, it could put a lot of pressure on the Celtics' defense and force them to make adjustments on the fly. The 76ers have a deep bench and a number of players who are capable of making big plays, so the Celtics will need to be prepared to face a balanced attack. On the other hand, if the Celtics can shut down the 76ers' stars and limit their scoring opportunities, it could be a long night for the home team.\n\nThe Celtics have been led by their own star players, who have been instrumental in their success so far in the series. Their ability to score from both inside and outside the paint has made them a difficult team to defend, and they have been able to take advantage of the 76ers' defensive weaknesses. However, the 76ers have made adjustments and have been able to limit the Celtics' scoring opportunities in recent games. The Celtics will need to be able to adapt and find new ways to score if they hope to come out on top in Game 6.\n\nAs the series has progressed, it has become clear that these two teams are evenly matched and that the outcome of each game is far from certain. The 76ers have shown a lot of heart and determination, and they have been able to stay in the series despite facing adversity. The Celtics, on the other hand, have been able to draw on their experience and depth to overcome challenges and come out on top. With the series on the line, both teams will be giving it their all in Game 6, and fans can expect a thrilling and intense contest.\n\nAs the NBA playoffs continue to heat up, the conclusion of the Celtics-76ers series is sure to be one of the most highly anticipated matchups of the week. With the possibility of a deciding Game 7 looming, both teams will be looking to give it their all and come out on top in Game 6. The energy at the Xfinity Mobile Arena is sure to be electric, and fans will be on the edge of their seats as they watch these two talented teams battle it out for a spot in the next round. As the clock ticks down to tipoff, one thing is certain: only one team will emerge victorious, and the stakes could not be higher.",
  "category": "Sports",
  "image": "https://images.actionnetwork.com/blog/2026/04/Celtics76ersG6.jpg",
  "image_source": "",
  "date": "2026-05-01T21:57:02Z",
  "tags": [
    "Sports"
  ],
  "source_url": "https://www.actionnetwork.com/nba/boston-celtics-vs-philadelphia-76ers-prediction-pick-odds-nba-playoffs-game-6-thursday-april-30",
  "discover": false
}