{
  "slug": "knicks-thrive-under-pressure-proving-their-mettle-this-season",
  "title": "Knicks Thrive Under Pressure, Proving Their Mettle This Season",
  "body": "The New York Knicks have once again demonstrated their ability to thrive under pressure, as they took a crucial 2-0 lead in the NBA Finals against the San Antonio Spurs. In a thrilling Game 2, the Knicks managed to overcome a 12-point deficit to emerge victorious, leaving the Spurs reeling. The turning point of the game came towards the end of the second quarter, when the Knicks' determination and resilience began to pay off, ultimately leading to a 4-point lead at halftime. This stunning turnaround has significant implications for the remainder of the series, as the Knicks' confidence and momentum continue to build.\n\nThe Knicks' ability to perform under pressure is a testament to their strength and character as a team. Despite facing a formidable opponent in the Spurs, they refused to back down, instead drawing on their collective experience and skill to mount a comeback. The team's leader, Stephon Castle, played a pivotal role in the game, although his absence from the court for a period of time raised concerns among Knicks fans. However, the team's depth and adaptability allowed them to adjust and continue pushing forward, ultimately securing a hard-fought win.\n\nThe Spurs, on the other hand, will be left to ponder what might have been, as they struggled to maintain their lead and capitalize on their early advantage. Despite their strong start, they were unable to withstand the Knicks' relentless pressure, and their offense began to falter as the game wore on. The Spurs' coaching staff will need to regroup and reassess their strategy, as they seek to find a way to counter the Knicks' potent offense and stem the tide of momentum that is currently flowing in favor of their opponents.\n\nThe NBA Finals series is now firmly in the Knicks' favor, as they take a commanding 2-0 lead into the next game. While the Spurs will be desperate to get back into the series, the Knicks will be looking to maintain their intensity and focus, as they seek to take a stranglehold on the championship. The Knicks' fans, meanwhile, will be ecstatic at the prospect of their team bringing home the title, and will be eagerly anticipating the next game in the series.\n\nAs the series heads into its next phase, the Knicks will be aware that they cannot afford to become complacent or take their foot off the gas. The Spurs are a proud and experienced team, and they will be determined to fight back and extend the series. However, the Knicks' current form and confidence suggest that they are well-equipped to handle the pressure and expectation that comes with being on the brink of a championship. With their sights firmly set on the title, the Knicks will be looking to continue their impressive run and bring the championship to New York.\n\nLooking ahead to the next game, it is clear that the Knicks are in a strong position to take control of the series. While the Spurs will be fighting to stay alive, the Knicks will be seeking to deliver the knockout blow and move one step closer to the championship. As the drama and excitement of the NBA Finals continue to unfold, one thing is certain: the New York Knicks are a team on a mission, and they will stop at nothing to achieve their goal of bringing home the title. With their skill, determination, and unwavering commitment to success, the Knicks are poised to make history and cement their place as one of the greatest teams in the NBA.",
  "category": "Sports",
  "image": "https://lede-admin.defector.com/wp-content/uploads/sites/28/2026/06/GettyImages-2280088845.jpg",
  "image_source": "",
  "date": "2026-06-08T22:29:13Z",
  "tags": [
    "Sports"
  ],
  "source_url": "https://defector.com/the-knicks-know-something-about-pressure",
  "discover": false
}