{
  "slug": "mlb-trade-rumors-ohearn-tolbert-ohtani-bichette-on-the-block",
  "title": "MLB Trade Rumors: O'Hearn, Tolbert, Ohtani, Bichette on the Block",
  "body": "In a thrilling display of power and precision, several Major League Baseball players made history on Tuesday, leaving fans and analysts alike in awe. The night's highlights were headlined by Ryan O'Hearn's monstrous performance, as the Pirates slugger shattered a franchise record with an astonishing 10 runs batted in against the Braves. Meanwhile, Shohei Ohtani achieved a milestone of his own, blasting his 300th career home run, a testament to his unwavering dedication and unrelenting passion for the game. Additionally, Tyler Tolbert of the Royals matched an MLB record for consecutive hits, further solidifying his reputation as a force to be reckoned with at the plate.\n\nO'Hearn's remarkable feat is a testament to his unbridled talent and clutch gene, as he single-handedly propelled the Pirates to a resounding victory. The grand slam and two three-run homers he hit within the first six innings of the game showcased his incredible ability to rise to the occasion and deliver under pressure. This breakout performance is likely to send shockwaves throughout the league, as O'Hearn's name becomes synonymous with power hitting and dominance. As the season progresses, it will be fascinating to see if he can maintain this level of production and lead the Pirates to a successful campaign.\n\nShohei Ohtani's 300th home run, on the other hand, is a landmark achievement that underscores his status as one of the most gifted and versatile players in the game. With this milestone, Ohtani joins an elite group of hitters who have reached this plateau, cementing his legacy as a truly transcendent talent. His ability to excel in multiple facets of the game, including pitching and hitting, makes him a unique asset to his team and a compelling figure to watch. As he continues to push the boundaries of what is possible, fans and pundits alike will be eagerly anticipating his next move.\n\nTyler Tolbert's record-tying streak of consecutive hits is another notable achievement that highlights the Royals' youngster's impressive skillset. Tolbert's ability to consistently get on base and create scoring opportunities for his team has been a vital component of the Royals' offense, and his record-tying feat is a testament to his growing reputation as a contact hitter extraordinaire. As he looks to build upon this impressive run, Tolbert will face increased scrutiny and attention from opposing pitchers, but his poise and confidence at the plate suggest that he is more than capable of rising to the challenge.\n\nIn addition to these individual accomplishments, Tuesday's games also shed light on the evolving landscape of the MLB. With several teams jostling for position in their respective divisions, the margin between success and failure is razor-thin. As the season enters its critical phase, players like O'Hearn, Ohtani, and Tolbert will be expected to continue delivering high-level performances, while their teams rely on them to drive momentum and secure crucial wins. The upcoming weeks and months promise to be filled with drama, excitement, and unexpected twists, as the MLB's best teams and players clash in a battle for supremacy.\n\nAs the baseball world looks to the future, one thing is certain \u2013 the bar has been set high, and the competition will only intensify from here. With O'Hearn, Ohtani, Tolbert, and other emerging stars leading the charge, the stage is set for a thrilling conclusion to the season. As fans and analysts eagerly anticipate the next installment of this captivating narrative, one question remains: what's next for these talented individuals, and how will their teams fare in the pursuit of greatness? Only time will tell, but one thing is certain \u2013 the MLB is in for a wild and unforgettable ride.",
  "category": "Sports",
  "image": "https://cdn.mlbtraderumors.com/files/2026/07/TylerTolbert-1-1024x684.jpg",
  "image_source": "",
  "date": "2026-07-09T15:14:48Z",
  "tags": [
    "Sports"
  ],
  "source_url": "https://www.mlbtraderumors.com/2026/07/the-opener-tolbert-ohtani-bichette.html",
  "discover": false
}