{
  "slug": "axolotl-the-salamander-that-can-regrow-its-brain",
  "title": "Axolotl: The Salamander That Can Regrow Its Brain",
  "body": "In a groundbreaking discovery that is set to revolutionize our understanding of regenerative biology, scientists have shed light on the extraordinary abilities of the axolotl, a unique species of salamander that possesses the remarkable capacity to regrow its own brain. This phenomenon, which has left researchers in awe, has significant implications for the field of neuroscience and raises hopes for the development of new treatments for a range of neurological disorders. The axolotl, with its feathery gills and perpetually youthful appearance, may appear harmless, but it harbors a secret that has the potential to transform our approach to brain damage and disease.\n\nThe axolotl's ability to regenerate its brain is a complex process that involves the coordinated effort of multiple cell types and tissues. Researchers have found that the salamander's brain contains a unique population of stem cells that are capable of differentiating into different types of neurons and glial cells, allowing it to repair and replace damaged tissue. This process is not only limited to the brain, as the axolotl is also capable of regrowing its limbs, eyes, and parts of its spinal cord, making it one of the most resilient creatures in the animal kingdom. The discovery of this remarkable ability has sparked intense interest among scientists, who are eager to unlock the secrets of the axolotl's regenerative powers and apply them to human medicine.\n\nOne of the most significant implications of the axolotl's brain regeneration ability is its potential to inform the development of new treatments for neurological disorders such as Parkinson's disease, Alzheimer's disease, and stroke. Currently, these conditions are often irreversible and can have a devastating impact on patients' quality of life. However, if scientists can crack the code of the axolotl's regenerative abilities, it may be possible to develop therapies that can repair or replace damaged brain tissue, restoring cognitive function and improving patient outcomes. Researchers are already exploring the possibility of using stem cells and other regenerative therapies to treat these conditions, and the axolotl's unique biology is providing a valuable roadmap for their research.\n\nDespite the excitement surrounding the axolotl's brain regeneration abilities, there is still much to be learned about this complex process. Researchers are working to understand the genetic and molecular mechanisms that underlie the salamander's regenerative powers, and to identify the key factors that enable it to regrow its brain and other tissues. This will require a multidisciplinary approach, involving experts from fields such as neuroscience, genetics, and developmental biology. However, the potential rewards are well worth the effort, as unlocking the secrets of the axolotl's regenerative abilities could lead to major breakthroughs in our understanding of human disease and the development of new treatments.\n\nThe discovery of the axolotl's brain regeneration abilities also highlights the importance of preserving biodiversity and protecting endangered species. The axolotl is native to Mexico and is currently listed as an endangered species due to habitat loss, pollution, and other environmental factors. As we continue to learn more about the axolotl's remarkable biology, it is essential that we take steps to conserve and protect this unique species, not only for its own sake but also for the potential benefits it could bring to human medicine. By working to preserve the axolotl and its habitat, we can help ensure that this remarkable creature continues to thrive and inspire scientific discovery for generations to come.\n\nAs researchers continue to unravel the mysteries of the axolotl's regenerative abilities, we can expect to see major advances in our understanding of brain development, disease, and repair. The potential for this research to lead to new treatments and therapies is vast, and it is likely that the axolotl will remain at the forefront of scientific inquiry for years to come. As we look to the future, it is clear that the axolotl's remarkable biology will continue to inspire and inform scientific discovery, and that its regenerative abilities will remain a powerful symbol of the incredible potential of the natural world to heal and transform human lives.",
  "category": "Science",
  "image": "https://imageio.forbes.com/specials-images/imageserve/6a0469ff4efb602c0d1c80d3/0x0.jpg?format=jpg&crop=1807,1017,x0,y93,safe&height=900&width=1600&fit=bounds",
  "image_source": "",
  "date": "2026-05-18T10:10:24Z",
  "tags": [
    "Science"
  ],
  "source_url": "https://www.forbes.com/sites/scotttravers/2026/05/16/meet-the-axolotl---the-salamander-that-can-regrow-its-own-brain/",
  "discover": false
}