{
  "slug": "felicious-ties-uncovering-the-fascinating-history-behind-humans-unlikely-bond-wi",
  "title": "Felicious Ties: Uncovering the Fascinating History Behind Humans' Unlikely Bond with Domestic Cats",
  "body": "Humans and cats have long been considered unlikely bedfellows, their relationship shifting from fierce predators to domestic companions over thousands of years. However, as researchers delve deeper into the intricate dynamics of our mutualism, a new perspective emerges: we may have inadvertently cultivated a parasite-like relationship with our feline friends. This notion challenges our conventional understanding of symbiotic relationships, prompting us to reevaluate the delicate balance between our species.\n\nAt its core, the relationship between humans and cats is built on mutual benefit. Cats provide pest control services, protecting our homes and crops from unwanted rodents and other small mammals. In return, we offer them sustenance, shelter, and affection. This arrangement has been successful for thousands of years, with cats adapting to their human environments and humans adapting to their feline companions. However, this symbiotic bond has also created a unique dynamic, one that blurs the lines between predator and prey.\n\nAccording to applied ecologist Rob Dunn, author of \"The Call of the Honeyguide,\" the human-cat relationship is a prime example of a mutually beneficial relationship that has evolved into a dependent one. Dunn argues that cats, having lost their natural hunting instincts, have become reliant on humans for food and care. This reliance creates a power imbalance, with humans inadvertently supporting the very species that were once their predators. This phenomenon is not unique to cats, as many species, including birds, insects, and even certain types of bacteria, have evolved to exploit human resources.\n\nThis notion of human-cat mutualism as a parasite-like relationship raises important questions about the long-term consequences of our actions. As we continue to domesticate and care for cats, are we inadvertently creating a species that is no longer capable of surviving on its own? This concern extends beyond cats, as we consider the broader implications of our relationships with other species. Have we, as humans, become unwitting hosts to a range of parasites, from the literal (e.g., fleas, ticks) to the metaphorical (e.g., our dependence on certain resources)?\n\nThe human-cat relationship also highlights the complexities of coexistence in the modern world. As urbanization and habitat fragmentation continue to alter ecosystems, we are forced to reevaluate our place within the natural world. By examining our relationships with other species, we can gain a deeper understanding of the delicate balance between humans and the environment.\n\nAs we move forward, it is essential to consider the long-term implications of our actions. By acknowledging the parasite-like nature of our relationship with cats, we can begin to reassess our role in the ecosystem and work towards a more sustainable coexistence. This requires a nuanced understanding of the complex dynamics at play, one that prioritizes mutual benefit over exploitation. By embracing this perspective, we may be able to forge a new path forward, one that balances our needs with those of the natural world.",
  "category": "Science",
  "image": "https://cdn.mos.cms.futurecdn.net/CQ2AJDH85dbZNMQ5hS9gHk-1600-80.jpg",
  "date": "2026-03-20T11:04:40Z",
  "tags": [
    "Science"
  ],
  "source_url": "https://www.livescience.com/animals/cats/parasites-of-human-societies-how-did-we-end-up-so-close-to-cats",
  "discover": false
}