{
  "slug": "relativity-space-to-develop-private-mars-orbiter-mission",
  "title": "Relativity Space to Develop Private Mars Orbiter Mission",
  "body": "In a groundbreaking move, a pioneering space technology company has unveiled ambitious plans to launch a privately developed Mars orbiter mission, slated for liftoff in 2028. This bold initiative marks a significant milestone in the pursuit of interplanetary exploration, as the private sector continues to play an increasingly vital role in advancing our understanding of the cosmos. The mission, which promises to expand our knowledge of the Red Planet, is poised to pave the way for a new era of collaborative space research and development.\n\nThe company's decision to embark on this complex and challenging endeavor is a testament to the growing capabilities and confidence of the private space industry. By leveraging cutting-edge technologies and innovative manufacturing techniques, the firm aims to demonstrate the feasibility and cost-effectiveness of privately developed planetary missions. This approach has the potential to revolutionize the field of space exploration, enabling more frequent and affordable access to other planets and celestial bodies. As the space industry continues to evolve, it is likely that we will see more companies following suit, driving innovation and pushing the boundaries of what is thought possible.\n\nThe Mars orbiter mission is expected to provide a wealth of new insights into the planet's geology, atmosphere, and potential habitability. By orbiting the planet, the spacecraft will be able to gather high-resolution imagery and data, shedding light on the Martian environment and its potential for supporting life. This information will be invaluable for scientists and researchers, who will be able to use it to inform future missions and advance our understanding of the planet. Furthermore, the success of this mission could have significant implications for the long-term exploration and potential colonization of Mars, which has been a topic of increasing interest and debate in recent years.\n\nThe announcement of this mission also highlights the growing trend of public-private partnerships in the space industry. As governments and space agencies face budget constraints and shifting priorities, private companies are stepping in to fill the gap, driving innovation and investment in space research and development. This collaborative approach has the potential to accelerate progress and achieve greater outcomes, as companies bring their expertise and resources to the table. However, it also raises important questions about the role of government in regulating and overseeing private space activities, ensuring that they align with national and international interests.\n\nAs the space industry continues to push the boundaries of exploration and discovery, it is likely that we will see more ambitious and complex missions being undertaken by private companies. The development of reusable rockets, advanced propulsion systems, and other technologies has made it possible for companies to undertake missions that were previously the exclusive domain of governments. This shift has significant implications for the future of space research and development, as private companies bring new ideas, approaches, and resources to the table. Whether it is the exploration of Mars, the Moon, or other destinations, the private sector is poised to play an increasingly vital role in shaping the future of space travel and discovery.\n\nLooking ahead, the success of this Mars orbiter mission could have far-reaching implications for the future of space exploration and development. As the private sector continues to drive innovation and investment in space research, we can expect to see more ambitious and complex missions being undertaken. With the potential for groundbreaking discoveries and new insights into the workings of our universe, the next decade is likely to be an exciting and transformative time for space research and development. As we embark on this new era of exploration and discovery, it will be fascinating to see how the private sector continues to shape the future of space travel and our understanding of the cosmos.",
  "category": "Science",
  "image": "https://spacenews.com/wp-content/uploads/2026/06/relativity-marsorbiter.jpeg",
  "image_source": "",
  "date": "2026-06-18T22:57:59Z",
  "tags": [
    "Science"
  ],
  "source_url": "https://spacenews.com/relativity-space-to-privately-develop-mars-orbiter-mission/",
  "discover": false
}