{
  "slug": "scientists-debunk-rattlesnake-myth-that-falsely-warned-hikers-and-doctors-for-de",
  "title": "Scientists Debunk Rattlesnake Myth That Falsely Warned Hikers and Doctors for Decades",
  "body": "For decades, hikers and medical professionals alike have been warned about the supposed dangers of baby rattlesnakes. The prevailing wisdom held that these young serpents were more aggressive and venomous than their adult counterparts, often attacking without warning. However, a recent study has shattered this long-held myth, revealing that the reality is far more innocuous. This revelation not only has significant implications for those who venture into rattlesnake country but also raises intriguing questions about how misconceptions can spread and persist.\n\nThe study's findings are based on a thorough examination of the behavior and biology of baby rattlesnakes. Researchers discovered that these young snakes are, in fact, less aggressive and less venomous than their adult counterparts. In many cases, baby rattlesnakes are more likely to retreat or flee when confronted, rather than striking out in self-defense. This new understanding of baby rattlesnakes challenges the popular narrative that they are inherently more menacing than their adult counterparts.\n\nSo, how did this widespread misconception arise? Experts suggest that a combination of factors contributed to the perpetuation of this myth. One possible explanation lies in the limited interactions between humans and rattlesnakes. When encounters do occur, they often involve adults, who are indeed more aggressive and venomous. This, in turn, may have led people to generalize and assume that all rattlesnakes, regardless of age, pose a significant threat. Additionally, anecdotal accounts and sensationalized media coverage may have further solidified this misconception in the public imagination.\n\nFurthermore, the study highlights the importance of separating fact from folklore. In an era where information is readily accessible and easily shared, the boundaries between scientific fact and popular myth can become increasingly blurred. This highlights the need for a more critical approach to information consumption and a greater emphasis on evidence-based knowledge.\n\nThe debunking of this rattlesnake myth also has practical implications for hikers, outdoor enthusiasts, and medical professionals. It underscores the importance of accurate information and informed decision-making in the face of potential dangers. By understanding the biology and behavior of baby rattlesnakes, individuals can better navigate and appreciate the natural world while minimizing the risks associated with encounters with these creatures.\n\nAs we move forward, it is essential to recognize the complex interplay between science, culture, and perception. This study serves as a reminder that even the most deeply ingrained myths can be challenged and overturned through rigorous research and critical inquiry. By embracing this spirit of inquiry and skepticism, we can foster a more informed and nuanced understanding of the world around us.",
  "category": "Science",
  "image": "https://scitechdaily.com/images/Prairie-Rattlesnake-Rock.jpg",
  "date": "2026-04-02T22:53:57Z",
  "tags": [
    "Science"
  ],
  "source_url": "https://scitechdaily.com/scientists-debunk-rattlesnake-myth-that-fooled-hikers-and-doctors-for-decades/",
  "discover": false
}