{
  "slug": "forza-horizon-6-more-than-just-racing",
  "title": "Forza Horizon 6: More than just racing",
  "body": "The highly anticipated Forza Horizon 6 is set to hit the gaming scene on May 19th, and fans of the open-world racing series are eagerly awaiting their chance to get behind the wheel. This latest installment promises to deliver a unique and immersive gaming experience, with a stunning virtual backdrop that showcases the breathtaking landscapes of Japan. As the gaming community counts down to the launch, it's clear that Forza Horizon 6 is more than just a racing game - it's an opportunity to embark on a virtual road trip of discovery and exploration.\n\nAt its core, Forza Horizon 6 is a game that celebrates the thrill of the open road, offering players the freedom to explore a beautifully rendered virtual world at their own pace. The game's Japanese setting provides a fascinating backdrop for this adventure, with its unique blend of traditional and modern landscapes. From the bustling streets of Tokyo to the serene countryside, the game's attention to detail and commitment to authenticity are sure to impress even the most seasoned gamers. Whether you're a racing enthusiast or simply looking for a new gaming experience, Forza Horizon 6 promises to deliver a level of depth and complexity that will keep you engaged for hours on end.\n\nOne of the key features that sets Forza Horizon 6 apart from other racing games is its emphasis on exploration. Rather than simply focusing on the thrill of the race, the game encourages players to take their time and soak in the sights and sounds of the virtual world. This approach is perfectly suited to the game's Japanese setting, where the unique culture and history of the country are waiting to be discovered. By providing players with the freedom to explore and discover new things, Forza Horizon 6 creates a sense of immersion and engagement that is hard to find in other games.\n\nThe game's stunning visuals and immersive soundtrack also play a key role in creating a believable and engaging gaming experience. The attention to detail in the game's graphics is impressive, with every aspect of the virtual world meticulously rendered to create a sense of realism and authenticity. The soundtrack, which features a mix of traditional and modern Japanese music, adds to the game's immersive atmosphere, drawing players into the world of the game and refusing to let go. Whether you're a fan of racing games or simply looking for a new gaming experience, Forza Horizon 6 is sure to impress with its stunning visuals and immersive soundtrack.\n\nAs the gaming community looks to the future, it's clear that Forza Horizon 6 is set to be one of the biggest releases of the year. With its unique blend of racing, exploration, and discovery, the game promises to deliver a gaming experience like no other. As players prepare to embark on their virtual road trip through Japan, they can expect a level of depth and complexity that will keep them engaged for hours on end. With its stunning visuals, immersive soundtrack, and emphasis on exploration, Forza Horizon 6 is the perfect game for anyone looking to experience the thrill of the open road.\n\nAs the launch of Forza Horizon 6 approaches, gamers around the world are eagerly anticipating their chance to get behind the wheel and experience the game's unique blend of racing and exploration. With its stunning virtual backdrop, immersive soundtrack, and emphasis on discovery, the game promises to deliver a gaming experience like no other. As the gaming community looks to the future, it's clear that Forza Horizon 6 is set to be one of the biggest releases of the year, and its impact will be felt for months to come. With its unique approach to gaming and commitment to authenticity, Forza Horizon 6 is sure to leave a lasting impression on the gaming world, and its influence will be felt for years to come.",
  "category": "Technology",
  "image": "https://platform.theverge.com/wp-content/uploads/sites/2/2026/05/assets_2026_01_1769110939_FH6_Screenshots_01-City-Night-Race.jpg?quality=90&strip=all&crop=0%2C3.4613147178592%2C100%2C93.077370564282&w=1200",
  "image_source": "",
  "date": "2026-05-15T16:56:44Z",
  "tags": [
    "Technology"
  ],
  "source_url": "https://www.theverge.com/entertainment/929816/forza-horizon-6-review-xbox-pc",
  "discover": false
}