{
  "slug": "revolutionary-tech-now-innovations-transforming-our-world",
  "title": "Revolutionary Tech Now: Innovations Transforming Our World",
  "body": "In a groundbreaking development that promises to revolutionize the field of prosthetics, a team of medical experts has been working tirelessly to test and refine cutting-edge technology that could significantly improve the lives of individuals with limb differences. At the forefront of this innovative endeavor is a pioneering medical expert who has been collaborating with a journalist to shed light on the vast potential of these futuristic prosthetics. Through a series of in-depth interviews and hands-on demonstrations, the expert has been showcasing the remarkable capabilities of these advanced prosthetic devices, which are designed to provide users with unprecedented levels of flexibility, dexterity, and control.\n\nThe medical expert's work in this field is built upon years of research and development, driven by a deep understanding of the complex needs and challenges faced by individuals with prosthetic limbs. By combining advanced materials, sophisticated sensors, and artificial intelligence, the team has created prosthetic devices that can be tailored to meet the unique requirements of each user. These customized prosthetics are capable of mimicking the natural movement and function of human limbs, allowing users to perform a wide range of tasks with greater ease and precision. From everyday activities like cooking and dressing to more complex actions like playing musical instruments or engaging in sports, these prosthetics have the potential to empower individuals with limb differences to live more independently and pursue their passions with renewed confidence.\n\nOne of the most significant advancements in this field is the development of prosthetic devices that can be controlled by the user's thoughts. Using electroencephalography (EEG) technology, these prosthetics can detect and interpret brain signals, allowing users to manipulate the device with remarkable accuracy. This innovation has far-reaching implications, as it could enable individuals with severe mobility impairments to interact with their environment in ways that were previously impossible. Moreover, the use of AI-powered algorithms enables the prosthetic device to learn and adapt to the user's behavior over time, fine-tuning its performance to meet their specific needs and preferences.\n\nAs the medical expert continues to test and refine these prosthetic devices, it is clear that the future of prosthetics holds tremendous promise. With the potential to restore mobility, independence, and dignity to individuals with limb differences, these advanced prosthetics are poised to make a profound impact on the lives of millions of people worldwide. Moreover, the technological advancements driving this field are likely to have a ripple effect, influencing innovations in other areas of healthcare and beyond. As researchers and developers push the boundaries of what is possible, we can expect to see even more exciting breakthroughs in the years to come.\n\nThe collaboration between the medical expert and the journalist has played a crucial role in raising awareness about the latest developments in prosthetic technology. By sharing their findings and insights with a wider audience, they hope to inspire a new generation of researchers, engineers, and innovators to join the quest for creating more advanced and accessible prosthetic devices. As the public becomes more informed and engaged, we can expect to see increased investment and support for this vital area of research, driving progress and accelerating the pace of innovation.\n\nLooking ahead, it is exciting to contemplate the possibilities that these futuristic prosthetics may hold. As the technology continues to evolve and improve, we can expect to see a significant increase in the quality of life for individuals with limb differences. With the potential to restore mobility, independence, and dignity, these advanced prosthetic devices are poised to make a lasting impact on the world. As we embark on this new frontier in prosthetic technology, it is clear that the future holds tremendous promise, and we can hardly wait to see the incredible advancements that are yet to come.",
  "category": "Technology",
  "image": "https://ichef.bbci.co.uk/images/ic/240x135/p0nmqxp4.jpg",
  "image_source": "",
  "date": "2026-06-26T22:19:58Z",
  "tags": [
    "Technology"
  ],
  "source_url": "https://www.bbc.co.uk/iplayer/episode/m002x058?at_medium=RSS&at_campaign=rss",
  "discover": true
}